<?xml version="1.0" encoding="UTF-8"?>
<!DOCTYPE document SYSTEM "..\..\..\Fabulae\core\dtd\dialogue.dtd">
<dialogue>
    <greeting id="greeting1">
        <text>
            LawEnfoncerDialogue.json#greeting1
        </text>
        <pcTalk id="pcTalk1" />
    </greeting>
    <pcTalk id="pcTalk1">
        <text>
            LawEnfoncerDialogue.json#pcTalk1
        </text>
        <npcTalk id="npcTalk1" />
    </pcTalk>
    <pcTalk id="pcTalk2" endOfConversation="true">
        <text>
            LawEnfoncerDialogue.json#pcTalk2
        </text>
    </pcTalk>
    <pcTalk id="pcTalk3" endOfConversation="true">
        <text>
            LawEnfoncerDialogue.json#pcTalk3
        </text>
    </pcTalk>
    <npcTalk id="npcTalk1">
        <text>
            LawEnfoncerDialogue.json#npcTalk1
        </text>
        <pcTalk id="pcTalk2" />
        <pcTalk id="pcTalk3" />
    </npcTalk>
</dialogue>